README.md
setup.py
aws_inventory/__init__.py
aws_inventory.egg-info/PKG-INFO
aws_inventory.egg-info/SOURCES.txt
aws_inventory.egg-info/dependency_links.txt
aws_inventory.egg-info/requires.txt
aws_inventory.egg-info/top_level.txt