Metadata-Version: 1.1
Name: aws-inventory
Version: 0.2.5
Summary: A dynamic AWS inventory for Ansible which groups nodes using regular expressions.
Home-page: https://github.com/zahna/aws_inventory
Author: Scott Zahn
Author-email: scott@zahna.com
License: License :: OSI Approved :: GNU General Public License v3 or later (GPLv3+)
Download-URL: https://pypi.python.org/pypi/aws_inventory
Platform: any
Classifier: Development Status :: 4 - Beta
Classifier: Operating System :: OS Independent
Classifier: Programming Language :: Python
Classifier: Programming Language :: Python :: 2
Classifier: Topic :: System :: Systems Administration
